{
  "chart_id": "line_280",
  "image_paths": {
    "no_grid": "charts/line/line_280.png",
    "with_grid": "charts/line/line_280_grid.png",
    "grid_with_grid": "charts/line/line_280_grid_with_grid.png"
  },
  "data_points": {
    "Actively disengaged": {
      "2002": 0.17,
      "2003": 0.17,
      "2004": 0.17,
      "2005": 0.15,
      "2006": 0.15,
      "2007": 0.2,
      "2008": 0.2,
      "2009": 0.18,
      "2010": 0.19,
      "2011": 0.19,
      "2012": 0.18
    },
    "Not engaged": {
      "2002": 0.53,
      "2003": 0.55,
      "2004": 0.54,
      "2005": 0.59,
      "2006": 0.55,
      "2007": 0.5,
      "2008": 0.51,
      "2009": 0.54,
      "2010": 0.53,
      "2011": 0.52,
      "2012": 0.52
    },
    "Engaged": {
      "2002": 0.3,
      "2003": 0.28,
      "2004": 0.29,
      "2005": 0.26,
      "2006": 0.3,
      "2007": 0.3,
      "2008": 0.29,
      "2009": 0.28,
      "2010": 0.28,
      "2011": 0.29,
      "2012": 0.3
    }
  },
  "x_ticks": [
    "2002",
    "2003",
    "2004",
    "2005",
    "2006",
    "2007",
    "2008",
    "2009",
    "2010",
    "2011",
    "2012"
  ],
  "y_ticks": [
    0.0,
    0.05,
    0.1,
    0.15,
    0.2,
    0.25,
    0.3,
    0.35,
    0.4,
    0.45,
    0.5,
    0.55,
    0.6
  ],
  "x_pixels": [
    134,
    187,
    239,
    291,
    344,
    396,
    448,
    501,
    553,
    605,
    658
  ],
  "y_pixels": [
    312,
    291,
    270,
    250,
    229,
    208,
    187,
    167,
    146,
    125,
    104,
    83,
    63
  ],
  "series_color": {
    "Actively disengaged": "#d62728",
    "Not engaged": "#9467bd",
    "Engaged": "#8c564b"
  }
}