{
  "chart_id": "line_207",
  "image_paths": {
    "no_grid": "charts/line/line_207.png",
    "with_grid": "charts/line/line_207_grid.png",
    "grid_with_grid": "charts/line/line_207_grid_with_grid.png"
  },
  "data_points": {
    "Rep/Lean Rep": {
      "7.0": 20.0,
      "8.0": 0.0,
      "9.0": 0.0,
      "10.0": 0.0,
      "nan": 4431.0,
      "13.0": 0.0,
      "15.0": 4431.0,
      "16.0": 4431.0
    }
  },
  "x_ticks": [
    "7.0",
    "8.0",
    "9.0",
    "10.0",
    "nan",
    "nan",
    "13.0",
    "nan",
    "15.0",
    "16.0"
  ],
  "y_ticks": [
    0.0,
    500.0,
    1000.0,
    1500.0,
    2000.0,
    2500.0,
    3000.0,
    3500.0,
    4000.0,
    4500.0,
    5000.0
  ],
  "x_pixels": [
    149,
    214,
    278,
    343,
    408,
    472,
    537,
    602,
    666,
    731
  ],
  "y_pixels": [
    314,
    288,
    263,
    238,
    212,
    187,
    162,
    136,
    111,
    85,
    60
  ],
  "series_color": {
    "Rep/Lean Rep": "#e377c2"
  }
}